lagraph.include/GraphBLAS.h
lagraph.include/LAGraph.h
lagraph.libs/libgraphblas.so.3.3.3
lagraph.libs/libgomp-a34b3233.so.1.0.0
lagraph.libs/liblagraph.so.0.1.0
lagraph-3.3.3.dist-info/top_level.txt
lagraph-3.3.3.dist-info/METADATA
lagraph-3.3.3.dist-info/RECORD
lagraph-3.3.3.dist-info/LICENSE
lagraph-3.3.3.dist-info/WHEEL
lagraph-3.3.3.data/purelib/lagraph/__init__.py
