Metadata-Version: 2.1
Name: lagraph
Version: 3.3.3
Summary: Python wheel containing prebuilt GraphBLAS/LAGraph shared libraries and header files.
Home-page: https://github.com/bergkvist/pylagraph
Author: Tobias Bergkvist
Author-email: tobias@bergkv.ist
License: MIT
Platform: unix
Platform: linux
Platform: osx
Classifier: Programming Language :: Python :: 3
License-File: LICENSE
